README.md
setup.py
lib/sigment/__init__.py
lib/sigment/base.py
lib/sigment/quantifiers.py
lib/sigment/transforms.py
lib/sigment.egg-info/PKG-INFO
lib/sigment.egg-info/SOURCES.txt
lib/sigment.egg-info/dependency_links.txt
lib/sigment.egg-info/requires.txt
lib/sigment.egg-info/top_level.txt
lib/sigment/internals/__init__.py
lib/sigment/internals/validator.py
lib/tests/__init__.py
lib/tests/lib/__init__.py
lib/tests/lib/internals/__init__.py
lib/tests/lib/internals/test_validator.py
lib/tests/lib/quantifiers/__init__.py
lib/tests/lib/transforms/__init__.py