Metadata-Version: 2.1
Name: sigment
Version: 0.1.1
Summary: An extensible data augmentation package for creating complex transformation pipelines for audio signals.
Home-page: https://github.com/eonu/sigment
Author: Edwin Onuonga
Author-email: ed@eonu.net
License: MIT
Project-URL: Documentation, https://notes.eonu.net/docs/sigment/
Project-URL: Bug Tracker, https://github.com/eonu/sigment/issues
Project-URL: Source Code, https://github.com/eonu/sigment
Platform: UNKNOWN
Classifier: Development Status :: 2 - Pre-Alpha
Classifier: Programming Language :: Python :: 3.6
Classifier: Programming Language :: Python :: 3.7
Classifier: Programming Language :: Python :: 3.8
Classifier: License :: OSI Approved :: MIT License
Classifier: Operating System :: Unix
Classifier: Operating System :: MacOS
Classifier: Intended Audience :: Science/Research
Classifier: Topic :: Software Development
Classifier: Topic :: Scientific/Engineering
Classifier: Natural Language :: English
Requires-Python: >=3.6,<=3.8
